{
  "verdict": "BATTLE48 traced GraphicRaycaster sort/display/pixelRect/mirror filtering after depth rebuild; final playable screen remains false",
  "visual_status": "raycast_ready_candidate_found_after_sort_display_trace",
  "isFinalRestoredBattleScreen": false,
  "unityExitCode": 0,
  "referenceVideoAvailable": false,
  "referenceVideoPath": "C:\\Users\\godho\\Downloads\\플레이.mp4",
  "auxiliaryReferenceVideoAvailable": true,
  "auxiliaryReferenceVideoPath": "C:\\Users\\godho\\Downloads\\참고.mp4",
  "unitySummary": {
    "status": "battle48_trace_sort_order_display_and_hit_occlusion_after_depth_rebuild",
    "isFinalRestoredBattleScreen": false,
    "sourceScene": "Assets/Scenes/Battle47GraphicDepthRaycastCandidateRegistration.unity",
    "scene": "Assets/Scenes/Battle48SortOrderDisplayHitOcclusionTrace.unity",
    "capture": "Assets/RestoreCaptures/battle_actor/Battle48SortOrderDisplayHitOcclusionTrace_1920x1080.png",
    "sourceSceneOpened": true,
    "sceneSaved": true,
    "captureExists": true,
    "reopenValid": true,
    "patchApplied": false,
    "prePatchPixelRectRejectedCount": 34,
    "prePatchMirrorTargetCandidateCount": 15,
    "summaryRowCount": 168,
    "detailRowCount": 3924,
    "reopenSummaryCount": 84,
    "reopenDepthNonNegativeCount": 60,
    "reopenAbsoluteDepthNonNegativeCount": 60,
    "reopenPixelRectContainsCount": 50,
    "reopenMirrorAnyCandidateCount": 15,
    "reopenMirrorTargetCandidateCount": 15,
    "reopenUnityHitPositiveCount": 15,
    "reopenRaycastReadyCount": 15,
    "bestRaycastReadyCount": 15,
    "primaryFailureSummary": "target_hit:15, no_mirror_candidates:35, event_camera_pixelrect_reject:34",
    "readyByPointSummary": "eventCamera_worldToScreen:5, b47_before_open_baseline:5, viewport_pixelRect:5, capture1920_scaled_to_camera640:0, camera640_scaled_to_capture1920:0, baseline_capture_scaled_to_camera640:0",
    "patchDecision": "candidate_point_hits_without_fake_overlay_validate_input_next",
    "failReason": ""
  },
  "rowSummary": {
    "summaryRowCount": 168,
    "detailRowCount": 3924,
    "reopenRowCount": 84,
    "reopenRaycastReadyCount": 15,
    "reopenUnityHitPositiveCount": 15,
    "reopenMirrorTargetCandidateCount": 15,
    "reopenMirrorAnyCandidateCount": 15,
    "reopenPixelRectContainsCount": 50,
    "reopenDepthNonNegativeCount": 60,
    "primaryFailureCounts": {
      "target_hit": 15,
      "no_mirror_candidates": 35,
      "event_camera_pixelrect_reject": 34
    },
    "pointCounts": {
      "eventCamera_worldToScreen": 14,
      "b47_before_open_baseline": 14,
      "viewport_pixelRect": 14,
      "capture1920_scaled_to_camera640": 14,
      "camera640_scaled_to_capture1920": 14,
      "baseline_capture_scaled_to_camera640": 14
    },
    "pointReadyCounts": {
      "eventCamera_worldToScreen": 5,
      "b47_before_open_baseline": 5,
      "viewport_pixelRect": 5
    },
    "detailRejectionCounts": {
      "final_candidate": 21,
      "rect_not_contains": 413,
      "raycastTarget_false": 338,
      "event_camera_pixelrect_reject": 1190
    },
    "targetDetailRejectionCounts": {
      "final_candidate": 15,
      "rect_not_contains": 15,
      "event_camera_pixelrect_reject": 25,
      "raycastTarget_false": 5
    },
    "detailFinalCandidateCount": 21,
    "targetDetailFinalCandidateCount": 15,
    "samples": [
      {
        "point": "eventCamera_worldToScreen",
        "button": "btnAuto",
        "pointer": "578/349",
        "pixelRectContains": "true",
        "targetDepth": "126",
        "mirrorTargetFinal": "true",
        "mirrorFinalCount": "1",
        "unityHitCount": "1",
        "ready": "true",
        "failure": "target_hit"
      },
      {
        "point": "b47_before_open_baseline",
        "button": "btnAuto",
        "pointer": "578/349",
        "pixelRectContains": "true",
        "targetDepth": "126",
        "mirrorTargetFinal": "true",
        "mirrorFinalCount": "1",
        "unityHitCount": "1",
        "ready": "true",
        "failure": "target_hit"
      },
      {
        "point": "viewport_pixelRect",
        "button": "btnAuto",
        "pointer": "578/349",
        "pixelRectContains": "true",
        "targetDepth": "126",
        "mirrorTargetFinal": "true",
        "mirrorFinalCount": "1",
        "unityHitCount": "1",
        "ready": "true",
        "failure": "target_hit"
      },
      {
        "point": "capture1920_scaled_to_camera640",
        "button": "btnAuto",
        "pointer": "192.667/155.111",
        "pixelRectContains": "true",
        "targetDepth": "126",
        "mirrorTargetFinal": "false",
        "mirrorFinalCount": "0",
        "unityHitCount": "0",
        "ready": "false",
        "failure": "no_mirror_candidates"
      },
      {
        "point": "camera640_scaled_to_capture1920",
        "button": "btnAuto",
        "pointer": "1734/785.25",
        "pixelRectContains": "false",
        "targetDepth": "126",
        "mirrorTargetFinal": "false",
        "mirrorFinalCount": "0",
        "unityHitCount": "0",
        "ready": "false",
        "failure": "event_camera_pixelrect_reject"
      },
      {
        "point": "baseline_capture_scaled_to_camera640",
        "button": "btnAuto",
        "pointer": "192.667/155.111",
        "pixelRectContains": "true",
        "targetDepth": "126",
        "mirrorTargetFinal": "false",
        "mirrorFinalCount": "0",
        "unityHitCount": "0",
        "ready": "false",
        "failure": "no_mirror_candidates"
      },
      {
        "point": "eventCamera_worldToScreen",
        "button": "btnBuff",
        "pointer": "578/439",
        "pixelRectContains": "true",
        "targetDepth": "124",
        "mirrorTargetFinal": "true",
        "mirrorFinalCount": "1",
        "unityHitCount": "1",
        "ready": "true",
        "failure": "target_hit"
      },
      {
        "point": "b47_before_open_baseline",
        "button": "btnBuff",
        "pointer": "578/439",
        "pixelRectContains": "true",
        "targetDepth": "124",
        "mirrorTargetFinal": "true",
        "mirrorFinalCount": "1",
        "unityHitCount": "1",
        "ready": "true",
        "failure": "target_hit"
      },
      {
        "point": "viewport_pixelRect",
        "button": "btnBuff",
        "pointer": "578/439",
        "pixelRectContains": "true",
        "targetDepth": "124",
        "mirrorTargetFinal": "true",
        "mirrorFinalCount": "1",
        "unityHitCount": "1",
        "ready": "true",
        "failure": "target_hit"
      },
      {
        "point": "capture1920_scaled_to_camera640",
        "button": "btnBuff",
        "pointer": "192.667/195.111",
        "pixelRectContains": "true",
        "targetDepth": "124",
        "mirrorTargetFinal": "false",
        "mirrorFinalCount": "0",
        "unityHitCount": "0",
        "ready": "false",
        "failure": "no_mirror_candidates"
      },
      {
        "point": "camera640_scaled_to_capture1920",
        "button": "btnBuff",
        "pointer": "1734/987.75",
        "pixelRectContains": "false",
        "targetDepth": "124",
        "mirrorTargetFinal": "false",
        "mirrorFinalCount": "0",
        "unityHitCount": "0",
        "ready": "false",
        "failure": "event_camera_pixelrect_reject"
      },
      {
        "point": "baseline_capture_scaled_to_camera640",
        "button": "btnBuff",
        "pointer": "192.667/195.111",
        "pixelRectContains": "true",
        "targetDepth": "124",
        "mirrorTargetFinal": "false",
        "mirrorFinalCount": "0",
        "unityHitCount": "0",
        "ready": "false",
        "failure": "no_mirror_candidates"
      },
      {
        "point": "eventCamera_worldToScreen",
        "button": "btnhelp",
        "pointer": "1308/557",
        "pixelRectContains": "false",
        "targetDepth": "110",
        "mirrorTargetFinal": "false",
        "mirrorFinalCount": "0",
        "unityHitCount": "0",
        "ready": "false",
        "failure": "event_camera_pixelrect_reject"
      },
      {
        "point": "b47_before_open_baseline",
        "button": "btnhelp",
        "pointer": "1308/557",
        "pixelRectContains": "false",
        "targetDepth": "110",
        "mirrorTargetFinal": "false",
        "mirrorFinalCount": "0",
        "unityHitCount": "0",
        "ready": "false",
        "failure": "event_camera_pixelrect_reject"
      },
      {
        "point": "viewport_pixelRect",
        "button": "btnhelp",
        "pointer": "1308/557",
        "pixelRectContains": "false",
        "targetDepth": "110",
        "mirrorTargetFinal": "false",
        "mirrorFinalCount": "0",
        "unityHitCount": "0",
        "ready": "false",
        "failure": "event_camera_pixelrect_reject"
      },
      {
        "point": "capture1920_scaled_to_camera640",
        "button": "btnhelp",
        "pointer": "436/247.556",
        "pixelRectContains": "true",
        "targetDepth": "110",
        "mirrorTargetFinal": "false",
        "mirrorFinalCount": "0",
        "unityHitCount": "0",
        "ready": "false",
        "failure": "no_mirror_candidates"
      },
      {
        "point": "camera640_scaled_to_capture1920",
        "button": "btnhelp",
        "pointer": "3924/1253.25",
        "pixelRectContains": "false",
        "targetDepth": "110",
        "mirrorTargetFinal": "false",
        "mirrorFinalCount": "0",
        "unityHitCount": "0",
        "ready": "false",
        "failure": "event_camera_pixelrect_reject"
      },
      {
        "point": "baseline_capture_scaled_to_camera640",
        "button": "btnhelp",
        "pointer": "436/247.556",
        "pixelRectContains": "true",
        "targetDepth": "110",
        "mirrorTargetFinal": "false",
        "mirrorFinalCount": "0",
        "unityHitCount": "0",
        "ready": "false",
        "failure": "no_mirror_candidates"
      }
    ]
  },
  "sceneYamlSummary": {
    "sceneExists": true,
    "empty4RaycastIdentifierCount": 7,
    "missingScriptFileId0Count": 1089
  },
  "battle47Carryover": {
    "visual_status": "graphic_depth_restored_but_raycast_still_not_ready",
    "reopenDepthNonNegativeCount": 10,
    "reopenRaycastReadyCount": 0
  },
  "captureMetrics": {
    "captureExists": true,
    "width": 1920,
    "height": 1080,
    "nonBlackPixelRatio": 0.899287
  },
  "battle47ToBattle48CaptureSimilarity": {
    "available": true,
    "meanAbsDiff": 0.0,
    "pixelCorrelation": 1.0
  },
  "blocker": "At least one original targetGraphic receives a GraphicRaycaster hit after reopen, but real input/click validation and reference alignment remain incomplete.",
  "nextBlocker": "BATTLE_49_VALIDATE_REAL_CLICK_INPUT_AND_HANDLER_BINDING",
  "rootCmdCount": 1,
  "restoreToolsDirectCmdCount": 0,
  "outputs": {
    "report": "C:\\Users\\godho\\Downloads\\girlswar\\reports\\battle\\BATTLE_48_TRACE_SORT_ORDER_DISPLAY_AND_HIT_OCCLUSION_AFTER_DEPTH_REBUILD_RESULT.md",
    "resultJson": "C:\\Users\\godho\\Downloads\\girlswar\\reports\\battle\\BATTLE_48_TRACE_SORT_ORDER_DISPLAY_AND_HIT_OCCLUSION_AFTER_DEPTH_REBUILD_RESULT.json",
    "unityDataJson": "C:\\Users\\godho\\Downloads\\girlswar\\girlswar_battle_unity\\Assets\\RestoreData\\battle\\BATTLE_48_TRACE_SORT_ORDER_DISPLAY_AND_HIT_OCCLUSION_AFTER_DEPTH_REBUILD_UNITY.json",
    "summaryCsv": "C:\\Users\\godho\\Downloads\\girlswar\\girlswar_battle_unity\\Assets\\RestoreData\\battle\\BATTLE_48_TRACE_SORT_ORDER_DISPLAY_AND_HIT_OCCLUSION_AFTER_DEPTH_REBUILD_TARGET_POINTS.csv",
    "detailCsv": "C:\\Users\\godho\\Downloads\\girlswar\\girlswar_battle_unity\\Assets\\RestoreData\\battle\\BATTLE_48_TRACE_SORT_ORDER_DISPLAY_AND_HIT_OCCLUSION_AFTER_DEPTH_REBUILD_REGISTERED_GRAPHICS.csv",
    "capture": "C:\\Users\\godho\\Downloads\\girlswar\\girlswar_battle_unity\\Assets\\RestoreCaptures\\battle_actor\\Battle48SortOrderDisplayHitOcclusionTrace_1920x1080.png",
    "contactSheet": "C:\\Users\\godho\\Downloads\\girlswar\\reports\\battle\\BATTLE_48_TRACE_SORT_ORDER_DISPLAY_AND_HIT_OCCLUSION_AFTER_DEPTH_REBUILD_CONTACT_SHEET.jpg",
    "unityLog": "C:\\Users\\godho\\Downloads\\girlswar\\reports\\battle\\BATTLE_48_TRACE_SORT_ORDER_DISPLAY_AND_HIT_OCCLUSION_AFTER_DEPTH_REBUILD.log"
  },
  "notes": [
    "BATTLE48 does not add fake transparent overlays, fake onClick handlers, fake HUD/cards/icons, screenshot paste, or whole-atlas placement.",
    "플레이.mp4 remains missing when referenceVideoAvailable is false; 참고.mp4 is auxiliary only.",
    "Depth rebuild was performed with a 640x480 render matching the eventCamera pixelRect; this preserves 640x480 eventCamera_worldToScreen coordinates for hit validation."
  ]
}